recomi/__init__.py
recomi/collecting.py
recomi/git.py
recomi/main.py
recomi/shared.py
recomi-1.2.1.dist-info/LICENCE.txt
recomi-1.2.1.dist-info/METADATA
recomi-1.2.1.dist-info/WHEEL
recomi-1.2.1.dist-info/entry_points.txt
recomi-1.2.1.dist-info/top_level.txt
recomi-1.2.1.dist-info/RECORD
