Metadata-Version: 2.1
Name: recomi
Version: 1.2.1
Summary: Repository Collection Mirror
Home-page: https://github.com/pscl4rke/recomi
Author: P. S. Clarke
Author-email: recomi@pscl4rke.net
Project-URL: Source Code, https://github.com/pscl4rke/recomi
Project-URL: Issues, https://github.com/pscl4rke/recomi/issues
Classifier: Development Status :: 5 - Production/Stable
Classifier: Environment :: Console
Classifier: Programming Language :: Python :: 3 :: Only
Classifier: Topic :: Software Development :: Version Control :: Git
Classifier: Topic :: System :: Archiving :: Backup
Classifier: Topic :: System :: Archiving :: Mirroring
Classifier: Topic :: Utilities
License-File: LICENCE.txt
Provides-Extra: dev
Requires-Dist: coverage ; extra == 'dev'
